xia_editor_flask/__init__.py
xia_editor_flask/editor.cpython-310-x86_64-linux-gnu.so
xia_editor_flask-0.1.1.dist-info/LICENSE.txt
xia_editor_flask-0.1.1.dist-info/METADATA
xia_editor_flask-0.1.1.dist-info/WHEEL
xia_editor_flask-0.1.1.dist-info/top_level.txt
xia_editor_flask-0.1.1.dist-info/RECORD
