Metadata-Version: 2.1
Name: xia-editor-flask
Version: 0.1.1
Summary: X-I-A
Home-page: https://develop.x-i-a.com/docs/xia-editor-flask/0.1.1/index.html
Author: X-I-A
Author-email: admin@x-i-a.com
License: UNKNOWN
Platform: UNKNOWN
Requires-Python: >=3.9
License-File: LICENSE.txt
Requires-Dist: Flask
Requires-Dist: xia-token-flask
Requires-Dist: xia-engine
